<?xml version="1.0" encoding="utf-8" ?><dwsync><file name="bread_1.jpg" server="uguratesyolda.org/httpdocs/" local="3570301860" remote="3570301860" Dst="-1" /><file name="bread_10.jpg" server="uguratesyolda.org/httpdocs/" local="3570301860" remote="3570301860" Dst="-1" /><file name="bread_11.jpg" server="uguratesyolda.org/httpdocs/" local="3570301920" remote="3570301920" Dst="-1" /><file name="bread_12.jpg" server="uguratesyolda.org/httpdocs/" local="3570301920" remote="3570301920" Dst="-1" /><file name="bread_2.jpg" server="uguratesyolda.org/httpdocs/" local="3570301920" remote="3570301920" Dst="-1" /><file name="bread_3.jpg" server="uguratesyolda.org/httpdocs/" local="3570301920" remote="3570301920" Dst="-1" /><file name="bread_4.jpg" server="uguratesyolda.org/httpdocs/" local="3570301920" remote="3570301920" Dst="-1" /><file name="bread_5.jpg" server="uguratesyolda.org/httpdocs/" local="3570301920" remote="3570301920" Dst="-1" /><file name="bread_6.jpg" server="uguratesyolda.org/httpdocs/" local="3570302040" remote="3570302040" Dst="-1" /><file name="bread_7.jpg" server="uguratesyolda.org/httpdocs/" local="3570301980" remote="3570301980" Dst="-1" /><file name="bread_8.jpg" server="uguratesyolda.org/httpdocs/" local="3570301980" remote="3570301980" Dst="-1" /><file name="bread_9.jpg" server="uguratesyolda.org/httpdocs/" local="3570302040" remote="3570302040" Dst="-1" /><file name="bread_ua13.jpg" server="uguratesyolda.org/httpdocs/" local="3570302040" remote="3570302040" Dst="-1" /></dwsync>